{"meta":{"iso":"MT","lang":"pl","translatedAt":"2026-07-10","engine":"opus-4-8","sourceHash":"4cd8695c9ead90e7bb9c72121aff2aec29e7f872c5297bfad74b6c2ee9b227f7","siteCountriesVersion":195,"stale":false},"fields":{"keyRules":["Maksymalnie 120 m nad poziomem gruntu (kategoria otwarta EASA)","Rejestracja jako operator UAS (25 €/rok lub 10 € za przepustkę turystyczną)","Wymagane szkolenie online A1/A3 — minimalny wiek 16 lat","Obowiązkowe ubezpieczenie od odpowiedzialności cywilnej dla dronów o dowolnej masie","CAŁY kraj to przestrzeń kontrolowana — zawsze sprawdzaj IDRONECT","Zawsze utrzymuj drona w zasięgu wzroku (VLOS)","Nigdy nie lataj nad ludźmi, tłumami ani imprezami publicznymi","CTR lotniska Malta International Airport obejmuje większość wyspy","Loty nocne zabronione bez szczególnego zezwolenia","Valletta i obszary zabytkowe: obowiązują dodatkowe ograniczenia"],"importantNotes":["CAŁY kraj to przestrzeń kontrolowana — sytuacja wyjątkowa w UE","Ubezpieczenie obowiązkowe dla dronów o dowolnej masie","CTR lotniska Malta Airport obejmuje większość głównej wyspy","Rejestracja turystyczna dostępna (10 €) dla odwiedzających na krótki pobyt","RODO ma zastosowanie przy uwiecznianiu wizerunku możliwych do zidentyfikowania osób"],"primaryLinks":[{"id":"tmcad_drones","url":"https://www.transport.gov.mt/aviation/civil-aviation-directorate/drones","title":"TM-CAD — Przepisy dronowe","description":"Oficjalne zasady dotyczące dronów Dyrekcji Lotnictwa Cywilnego Transport Malta"},{"id":"tmcad_register","url":"https://www.transport.gov.mt/aviation/civil-aviation-directorate/drones","title":"TM-CAD — Rejestracja jako operator","description":"Rejestracja jako operator UAS (25 €/rok lub 10 € turystycznie, ważna we wszystkich krajach UE/EASA)"},{"id":"idronect","url":"https://tmcad.idronect.com","title":"IDRONECT — Zarządzanie lotami","description":"Platforma do planowania i zatwierdzania lotów dronów na Malcie"},{"id":"tmcad_rules","url":"https://www.transport.gov.mt/aviation/civil-aviation-directorate/drones","title":"TM-CAD — Przegląd zasad","description":"Przegląd zasad latania dronami na Malcie"}],"secondaryLinks":[{"id":"mats","url":"https://www.maltats.com","title":"MATS — Służby ruchu lotniczego","description":"Maltańskie służby ruchu lotniczego oraz informacje o przestrzeni powietrznej"},{"id":"tmcad_faq","url":"https://www.transport.gov.mt/aviation/civil-aviation-directorate/drones","title":"TM-CAD — Najczęściej zadawane pytania o drony","description":"Najczęściej zadawane pytania dotyczące przepisów dronowych na Malcie"}],"disclaimerText":"Przed lotem zawsze sprawdzaj oficjalne źródła TM-CAD oraz IDRONECT. Ta aplikacja jest narzędziem, a nie organem prawnym. Malta stosuje przepisy EASA — pamiętaj, że cały kraj to przestrzeń kontrolowana.","sectionLabelRules":"KLUCZOWE ZASADY (KATEGORIA OTWARTA EASA)","sectionLabelPrimary":"ŹRÓDŁA OFICJALNE","sectionLabelSecondary":"DODATKOWE MATERIAŁY","linksSheetTitle":"Przestrzeń powietrzna i zasady — Malta","dronePilotCredentialName":"Świadectwo pilota bezzałogowego statku powietrznego","checklist":null}}