{"meta":{"iso":"HK","lang":"fr","translatedAt":"2026-07-10","engine":"opus-4-8","sourceHash":"bc6fff4fc63af5ac05aea5de894f5787","siteCountriesVersion":198,"stale":false},"fields":{"keyRules":["Maximum 91 m (300 ft) au-dessus du sol — plus bas que dans la plupart des pays","Enregistrement requis pour tous les drones de plus de 250 g via le portail eSUA","Formation Advanced Rating requise pour les drones de plus de 250 g","Assurance OBLIGATOIRE : 10 M HK$ pour les drones de plus de 7 kg, 5 M HK$ pour 250 g–7 kg","5 km des aéroports — interdiction de voler sans l'autorisation du CAD","Distance minimale de 50 m des personnes non impliquées","De jour uniquement — pas de vol de nuit sans autorisation spéciale","La zone du port Victoria est réglementée","Gardez toujours une vue directe (VLOS)","Hong Kong a ses propres règles — PAS celles de la Chine continentale"],"importantNotes":["L'altitude maximale n'est que de 91 m (300 ft) — nettement inférieure aux 120 m standard de la plupart des pays","L'assurance est obligatoire et coûteuse : couverture de 10 M HK$ pour les drones de plus de 7 kg","Hong Kong a des règles totalement distinctes de celles de la Chine continentale","Le port Victoria et les zones environnantes font l'objet de restrictions de vol","Catégorie C (25–150 kg) introduite en juillet 2025 pour la livraison commerciale et les opérations eVTOL — certification distincte requise"],"primaryLinks":[{"id":"cad_sua","url":"https://www.cad.gov.hk/english/sua.html","title":"CAD — Réglementation des petits UA","description":"Règles et directives officielles sur les drones du Département de l'aviation civile pour Hong Kong"},{"id":"esua_portal","url":"https://esua.cad.gov.hk/","title":"eSUA — Portail d'enregistrement","description":"Enregistrez votre drone et demandez des autorisations de vol en ligne"},{"id":"cad_drone_map","url":"https://esua.cad.gov.hk/web/droneMap","title":"CAD — Carte des drones","description":"Carte officielle des drones indiquant les zones réglementées, les aéroports et les zones autorisées"}],"secondaryLinks":[{"id":"cad_advanced","url":"https://www.cad.gov.hk/english/sua.html","title":"CAD — Formation Advanced Rating","description":"Formation Advanced Rating requise pour les drones de plus de 250 g"},{"id":"cad_insurance","url":"https://www.cad.gov.hk/english/sua.html","title":"CAD — Exigences d'assurance","description":"Exigences d'assurance responsabilité civile obligatoire pour les opérations de drones"}],"disclaimerText":"Vérifiez toujours les sources officielles du CAD avant de voler. Cette application est un outil, pas une autorité juridique. Hong Kong a sa propre réglementation des drones — les règles de la Chine continentale ne s'appliquent pas.","sectionLabelRules":"RÈGLES CLÉS","sectionLabelPrimary":"SOURCES OFFICIELLES","sectionLabelSecondary":"RESSOURCES COMPLÉMENTAIRES","linksSheetTitle":"Espace aérien et règles — Hong Kong","dronePilotCredentialName":"Qualification de télépilote SUA","checklist":null}}