{"meta":{"iso":"HU","lang":"da","translatedAt":"2026-07-10","engine":"opus-4-8","sourceHash":"421d031f59ae2f2836dd8bfaee823a0d5e5802e491b0aff2fec48fea0ff77951","siteCountriesVersion":195,"stale":false},"fields":{"keyRules":["Maksimalt 120 m over jorden (EASA Åben kategori)","Registrering er påkrævet for droner på 120 g eller mere (et strengere krav end EASA's grænse på 250 g)","A1/A3-onlinekurset er obligatorisk — minimumsalder 16 år","Obligatorisk ansvarsforsikring for al droneflyvning","Budapest: tilladelse til byflyvning skal søges 30 dage i forvejen","Appen MyDroneSpace er påkrævet ved hver flyvning","Hold altid dronen inden for synsvidde (VLOS)","Flyv aldrig over mennesker, folkemængder eller offentlige arrangementer","Mindst 5 km fra enhver lufthavn eller landingsplads","Parlamentet, regeringsbygninger og militære områder: absolut flyveforbud"],"importantNotes":["Registrering er nu obligatorisk for droner på 120 g eller mere — et langt strengere krav end EASA's standardgrænse på 250 g","I Budapest skal du søge om tilladelse 30 dage i forvejen — planlæg i god tid","Appen MyDroneSpace er påkrævet ved hver flyvning","Ansvarsforsikring er obligatorisk for alle droner, uanset vægt","GDPR gælder, hvis du indsamler data om personer, der kan identificeres"],"primaryLinks":[{"id":"hc_drones","url":"https://ais-en.hungarocontrol.hu/uas-airspace-restrictions","title":"HungaroControl — droneregler","description":"Officielle droneregler og retningslinjer fra den ungarske flyvekontroltjeneste"},{"id":"mydronespace","url":"https://mydronespace.hu","title":"MyDroneSpace — registrering og flyvning","description":"App til registrering og flyvestyring (påkrævet ved alle flyvninger)"},{"id":"hc_map","url":"https://mydronespace.hu","title":"MyDroneSpace — luftkort","description":"Officielt interaktivt kort med dronezoner og luftrumsrestriktioner"},{"id":"hc_rules","url":"https://ais-en.hungarocontrol.hu/uas-airspace-restrictions","title":"HungaroControl — oversigt over reglerne","description":"En oversigt over dronereglerne i Ungarn"}],"secondaryLinks":[{"id":"kozlekedesi","url":"https://www.kozlekedesihatosag.kormany.hu","title":"Luftfartsmyndigheden — licenser","description":"Information om licenser fra den ungarske civile luftfartsmyndighed"},{"id":"hc_faq","url":"https://ais-en.hungarocontrol.hu/uas-airspace-restrictions","title":"HungaroControl — ofte stillede spørgsmål om droner","description":"Ofte stillede spørgsmål om de ungarske droneregler"}],"disclaimerText":"Tjek altid HungaroControls officielle kilder samt MyDroneSpace, før du flyver. Denne app er kun et værktøj — den er ikke en juridisk myndighed. Ungarn følger EASA-reglerne med strenge nationale tilføjelser.","sectionLabelRules":"VIGTIGSTE REGLER (EASA ÅBEN KATEGORI)","sectionLabelPrimary":"OFFICIELLE KILDER","sectionLabelSecondary":"YDERLIGERE RESSOURCER","linksSheetTitle":"Luftrum og regler — Ungarn","dronePilotCredentialName":"Dronepilotcertificering","checklist":null}}