{"meta":{"iso":"FI","lang":"sk","translatedAt":"2026-07-10","engine":"opus-4-8","sourceHash":"6fb1ee677a0b80fd8bbda53044ed75ff332e45bfebaeaec42f4f27f9b7a6e00c","siteCountriesVersion":198,"stale":false},"fields":{"keyRules":["Najviac 120 m nad úrovňou terénu (kategória EASA Open)","Registrácia ako používateľ UAS (€30 na 3 roky alebo €100 na 5 rokov), ak váš dron váži aspoň 250 g alebo je vybavený kamerou","Vyžaduje sa online školenie A1/A3 – minimálny vek 16 rokov","Dron majte vždy vo vizuálnom dohľade (VLOS)","Nikdy nelietajte nad ľuďmi, davmi ani verejnými podujatiami","Dodržiavajte obmedzenia pre CTR letísk a zóny vzdušného priestoru UAS — skontrolujte Droneinfo.fi","Nočné lety sú povolené, ak má dron zelené blikajúce identifikačné svetlo a viditeľnosť je dostatočná","V blízkosti východnej hranice platia letové obmedzenia — pred letom si overte dotknuté oblasti","V Laponsku môžu v oblastiach chovu sobov platiť sezónne obmedzenia","Skontrolujte Droneinfo.fi pre obmedzenia a výškové limity špecifické pre danú oblasť"],"importantNotes":["Registrácia stojí 30 € na 3 roky alebo 100 € na 5 rokov","Zóna východnej hranice (EFR100) je aktívna 24 hodín denne — teraz viditeľná na mape","Zóny UAS úradu Traficom a oblasti Natura 2000 sú zobrazené na mape","V zime kapacita batérie v mrazivých teplotách klesá","Biele noci: dlhé letové časy, no nezabudnite skontrolovať obmedzené oblasti","Na fotografovanie identifikovateľných osôb sa vzťahuje legislatíva o ochrane údajov (GDPR)"],"primaryLinks":[{"id":"traficom_drones","url":"https://droneinfo.fi/en/droneinfo-front-page","title":"Traficom – Pravidlá pre drony","description":"Oficiálne predpisy pre drony fínskej agentúry pre dopravu a spoje (Traficom)"},{"id":"traficom_register","url":"https://droneinfo.fi/en/registering-drone-operator","title":"Traficom – Registrácia","description":"Registrácia ako používateľ UAS (€30 na 3 roky alebo €100 na 5 rokov, platná vo všetkých krajinách EÚ/EASA)"},{"id":"droneinfo","url":"https://www.droneinfo.fi","title":"Droneinfo.fi – Mapa vzdušného priestoru","description":"Oficiálna interaktívna mapa dronov zobrazujúca bezletové a obmedzené zóny"},{"id":"traficom_training","url":"https://droneinfo.fi/en/droneinfo-front-page","title":"Traficom – Školenia a skúšky","description":"Informácie o školeniach a skúškach A1/A3 a A2"}],"secondaryLinks":[{"id":"fintraffic","url":"https://www.fintraffic.fi/en/ans","title":"Fintraffic ANS – Informácie o vzdušnom priestore","description":"Fínske riadenie letovej prevádzky a informácie o vzdušnom priestore"},{"id":"traficom_faq","url":"https://droneinfo.fi/en/droneinfo-front-page","title":"Traficom – Často kladené otázky o dronoch","description":"Často kladené otázky o fínskych predpisoch pre drony"}],"disclaimerText":"Pred lietaním vždy skontrolujte oficiálne zdroje úradu Traficom a Droneinfo.fi. Táto aplikácia je nástroj, nie oficiálny orgán. Fínsko dodržiava predpisy EASA s ďalšími národnými požiadavkami.","sectionLabelRules":"KĽÚČOVÉ PRAVIDLÁ (KATEGÓRIA EASA OPEN)","sectionLabelPrimary":"OFICIÁLNE ZDROJE","sectionLabelSecondary":"ĎALŠIE INFORMÁCIE","linksSheetTitle":"Vzdušný priestor a pravidlá — Fínsko","dronePilotCredentialName":"Osvedčenie diaľkovo riadiaceho prevádzkovateľa","checklist":null}}