{"meta":{"iso":"GR","lang":"is","translatedAt":"2026-07-10","engine":"opus-4-8","sourceHash":"9aa97e145aa4835f384076255224fa15bd4f778e4fd7dfb570e7e98a5d6aa4f1","siteCountriesVersion":195,"stale":false},"fields":{"keyRules":["Að hámarki 120 m yfir jörðu (EASA opinn flokkur)","Skráðu þig sem rekstraraðili fjarstýrðra loftfara (ókeypis), ef dróninn vegur 250 g eða meira eða er með myndavél","A1/A3 netþjálfun er nauðsynleg – lágmarksaldur 16","Skyldubundin fyrirframtilkynning 5 dögum fyrir öll flug","Takmörkuð fornleifasvæði: Akrópólis, Delfí, Ólympía og fleiri","Haltu ávallt sjónlínu (VLOS) við drónann","Fljúgðu aldrei yfir fólk, mannfjölda eða opinbera viðburði","Lágmarksfjarlægð 8 km frá hverjum flugvelli","Næturflug er bannað án sérstaks leyfis","Flugvellir á eyjum: athugaðu DAGR-kortið vandlega — margar eyjar hafa stór stýrð svæði (CTR)"],"importantNotes":["Skyldubundin 5 daga fyrirframtilkynning fyrir ÖLL flug","Fornleifasvæði og menningarminjar eru stranglega bannaðar — þungar sektir gilda","Flugvellir á eyjum skapa umfangsmikil takmörkuð svæði","Hermannvirki: algjör flugbannssvæði (mörg á eyjum)","GDPR gildir þegar teknar eru myndir af persónugreinanlegum einstaklingum"],"primaryLinks":[{"id":"hcaa_drones","url":"https://hcaa.gov.gr/en/where-you-are-allowed-fly-uas-greece","title":"HCAA – Reglur um dróna","description":"Opinberar reglur og upplýsingar frá flugmálayfirvöldum um dróna"},{"id":"hcaa_register","url":"https://hcaa.gov.gr/en/where-you-are-allowed-fly-uas-greece","title":"HCAA – Skráning flugmanns","description":"Ókeypis skráning sem rekstraraðili fjarstýrðra loftfara (gildir í öllum ESB/EASA-löndum)"},{"id":"dagr","url":"https://dagr.hasp.gov.gr","title":"DAGR – Loftrýmiskort fyrir dróna","description":"Opinbert landfræðilegt kort af takmörkunum á drónaflugi í Grikklandi"},{"id":"hcaa_notification","url":"https://hcaa.gov.gr/en/where-you-are-allowed-fly-uas-greece","title":"HCAA – Flugtilkynning","description":"Skil á 5 daga fyrirframtilkynningu um flug (nauðsynleg fyrir hvert flug)"}],"secondaryLinks":[{"id":"hasp","url":"https://www.hasp.gov.gr","title":"HASP – Loftíþróttir","description":"Loftíþróttasamband Grikklands og upplýsingar um tómstundaflug"},{"id":"hcaa_faq","url":"https://hcaa.gov.gr/en/where-you-are-allowed-fly-uas-greece","title":"HCAA – Algengar spurningar um dróna","description":"Algengar spurningar um drónareglur í Grikklandi"}],"disclaimerText":"Athugaðu ávallt opinberar heimildir Flugmálastjórnar Grikklands (HCAA) og DAGR-kortið fyrir hvert flug. Þetta forrit er verkfæri — ekki lögbær heimild. Grikkland fylgir EASA-reglunum með viðbótum á landsvísu, þar á meðal meðal annars skyldubundinni 5 daga flugtilkynningu.","sectionLabelRules":"GRUNNREGLUR (EASA OPINN FLOKKUR)","sectionLabelPrimary":"OPINBERAR HEIMILDIR","sectionLabelSecondary":"VIÐBÓTARÚRRÆÐI","linksSheetTitle":"Loftrými og reglur — Grikkland","dronePilotCredentialName":"Rekstrarvottorð","checklist":null}}